{
  "encoding": {
    "x": {
      "field": "Origin",
      "type": "nominal",
      "primitiveType": "string",
      "selected": true,
      "_any": false,
      "scale": {
        "bandSize": 30
      }
    },
    "y": {
      "field": "Miles_per_Gallon",
      "type": "quantitative",
      "scale": {
        "bandSize": 30
      }
    }
  },
  "config": {
    "background": "white",
    "cell": {
      "width": 400,
      "height": 400
    }
  },
  "mark": "tick",
  "data": {
    "url": "file:///Users/jpocom/Projects/Diagram/chart-generator/data/cars.json",
    "formatType": "json"
  },
  "_info": {
    "score": 0.76032,
    "features": [
      {
        "reason": "x=Origin,N [ ]",
        "score": 0.99
      },
      {
        "reason": "y=Miles_per_Gallon,Q [ ]",
        "score": 1
      },
      {
        "reason": "OxQ plot",
        "score": 0.8
      },
      {
        "reason": "mark=tick",
        "score": 0.96
      }
    ]
  }
}